{
  "datasources": [
    {
      "id": 1,
      "org_id": 1,
      "type": "prometheus",
      "name": "prometheus",
      "access": "proxy",
      "url": "http://localhost:9090",
      "database": "",
      "basic_auth": 0,
      "is_default": 0,
      "json_data": "{\"pdcInjected\":false}",
      "uid": "ffc1blz1fjtoga",
      "created": "2026-02-02 14:40:44",
      "updated": "2026-02-02 14:41:01"
    },
    {
      "id": 2,
      "org_id": 1,
      "type": "prometheus",
      "name": "Prometheus",
      "access": "proxy",
      "url": "http://localhost:9090",
      "database": "",
      "basic_auth": 0,
      "is_default": 1,
      "json_data": "{\"httpMethod\":\"POST\",\"timeInterval\":\"15s\"}",
      "uid": "dfc1brpumwo3kc",
      "created": "2026-02-02 14:42:32",
      "updated": "2026-02-02 14:42:32"
    },
    {
      "id": 3,
      "org_id": 1,
      "type": "marcusolsson-json-datasource",
      "name": "S3 Statistics",
      "access": "proxy",
      "url": "https://quest.apidataupload.com",
      "database": "",
      "basic_auth": 0,
      "is_default": 0,
      "json_data": "{\"apiVersion\":\"1.0\",\"httpHeaderName1\":\"x-api-key\"}",
      "uid": "bfc1cyfos74sgd",
      "created": "2026-02-02 14:55:50",
      "updated": "2026-02-02 16:33:10"
    }
  ]
}