{
  "panels": [
    {
      "fieldConfig": {
        "defaults": {
          "color": {
            "mode": "thresholds"
          },
          "decimals": 0,
          "thresholds": {
            "mode": "absolute",
            "steps": [
              {
                "color": "green",
                "value": null
              }
            ]
          },
          "unit": "none"
        }
      },
      "gridPos": {
        "h": 4,
        "w": 4,
        "x": 0,
        "y": 0
      },
      "id": 1,
      "targets": [
        {
          "datasource": {
            "type": "marcusolsson-json-datasource",
            "uid": "bfc1cyfos74sgd"
          },
          "fields": [
            {
              "jsonPath": "$.overview.totalFiles",
              "name": "Files"
            }
          ],
          "method": "GET",
          "queryType": "query",
          "refId": "A",
          "urlPath": "/api/s3-stats"
        }
      ],
      "title": "Total Files",
      "type": "stat"
    },
    {
      "fieldConfig": {
        "defaults": {
          "color": {
            "mode": "thresholds"
          },
          "decimals": 2,
          "thresholds": {
            "mode": "absolute",
            "steps": [
              {
                "color": "green",
                "value": null
              },
              {
                "color": "yellow",
                "value": 50
              },
              {
                "color": "orange",
                "value": 100
              },
              {
                "color": "red",
                "value": 200
              }
            ]
          },
          "unit": "decgbytes"
        }
      },
      "gridPos": {
        "h": 4,
        "w": 4,
        "x": 4,
        "y": 0
      },
      "id": 2,
      "targets": [
        {
          "datasource": {
            "type": "marcusolsson-json-datasource",
            "uid": "bfc1cyfos74sgd"
          },
          "fields": [
            {
              "jsonPath": "$.overview.totalSizeGB",
              "name": "Size GB"
            }
          ],
          "method": "GET",
          "queryType": "query",
          "refId": "A",
          "urlPath": "/api/s3-stats"
        }
      ],
      "title": "Total Storage",
      "type": "stat"
    },
    {
      "fieldConfig": {
        "defaults": {
          "color": {
            "mode": "thresholds"
          },
          "decimals": 0,
          "thresholds": {
            "mode": "absolute",
            "steps": [
              {
                "color": "green",
                "value": null
              }
            ]
          },
          "unit": "none"
        }
      },
      "gridPos": {
        "h": 4,
        "w": 4,
        "x": 8,
        "y": 0
      },
      "id": 3,
      "options": {
        "text": {},
        "textMode": "value_and_name"
      },
      "targets": [
        {
          "datasource": {
            "type": "marcusolsson-json-datasource",
            "uid": "bfc1cyfos74sgd"
          },
          "fields": [
            {
              "jsonPath": "$.sessions.complete",
              "name": "Complete"
            },
            {
              "jsonPath": "$.sessions.total",
              "name": "Total"
            }
          ],
          "method": "GET",
          "queryType": "query",
          "refId": "A",
          "urlPath": "/api/s3-stats"
        }
      ],
      "title": "Complete Sessions",
      "type": "stat"
    },
    {
      "fieldConfig": {
        "defaults": {
          "color": {
            "mode": "thresholds"
          },
          "decimals": 2,
          "thresholds": {
            "mode": "absolute",
            "steps": [
              {
                "color": "green",
                "value": null
              },
              {
                "color": "yellow",
                "value": 5
              },
              {
                "color": "orange",
                "value": 10
              },
              {
                "color": "red",
                "value": 20
              }
            ]
          },
          "unit": "currencyUSD"
        }
      },
      "gridPos": {
        "h": 4,
        "w": 4,
        "x": 12,
        "y": 0
      },
      "id": 4,
      "targets": [
        {
          "datasource": {
            "type": "marcusolsson-json-datasource",
            "uid": "bfc1cyfos74sgd"
          },
          "fields": [
            {
              "jsonPath": "$.costs.currentMonthly",
              "name": "Cost"
            }
          ],
          "method": "GET",
          "queryType": "query",
          "refId": "A",
          "urlPath": "/api/s3-stats"
        }
      ],
      "title": "Monthly Cost (S3 Standard)",
      "type": "stat"
    },
    {
      "fieldConfig": {
        "defaults": {
          "color": {
            "mode": "thresholds"
          },
          "decimals": 0,
          "thresholds": {
            "mode": "absolute",
            "steps": [
              {
                "color": "green",
                "value": null
              },
              {
                "color": "yellow",
                "value": 1
              },
              {
                "color": "orange",
                "value": 3
              },
              {
                "color": "red",
                "value": 5
              }
            ]
          },
          "unit": "none"
        }
      },
      "gridPos": {
        "h": 4,
        "w": 4,
        "x": 16,
        "y": 0
      },
      "id": 5,
      "targets": [
        {
          "datasource": {
            "type": "marcusolsson-json-datasource",
            "uid": "bfc1cyfos74sgd"
          },
          "fields": [
            {
              "jsonPath": "$.sessions.incomplete",
              "name": "Incomplete"
            }
          ],
          "method": "GET",
          "queryType": "query",
          "refId": "A",
          "urlPath": "/api/s3-stats"
        }
      ],
      "title": "Incomplete Sessions",
      "type": "stat"
    },
    {
      "fieldConfig": {
        "defaults": {
          "color": {
            "mode": "thresholds"
          },
          "decimals": 1,
          "thresholds": {
            "mode": "absolute",
            "steps": [
              {
                "color": "blue",
                "value": null
              }
            ]
          },
          "unit": "decmbytes"
        }
      },
      "gridPos": {
        "h": 4,
        "w": 4,
        "x": 20,
        "y": 0
      },
      "id": 6,
      "targets": [
        {
          "datasource": {
            "type": "marcusolsson-json-datasource",
            "uid": "bfc1cyfos74sgd"
          },
          "fields": [
            {
              "jsonPath": "$.overview.averageFileSizeMB",
              "name": "Avg Size"
            }
          ],
          "method": "GET",
          "queryType": "query",
          "refId": "A",
          "urlPath": "/api/s3-stats"
        }
      ],
      "title": "Avg File Size",
      "type": "stat"
    },
    {
      "gridPos": {
        "h": 8,
        "w": 8,
        "x": 0,
        "y": 4
      },
      "id": 7,
      "options": {
        "legend": {
          "displayMode": "table",
          "placement": "right",
          "values": [
            "value",
            "percent"
          ]
        },
        "pieType": "pie",
        "tooltip": {
          "mode": "multi"
        }
      },
      "targets": [
        {
          "datasource": {
            "type": "marcusolsson-json-datasource",
            "uid": "bfc1cyfos74sgd"
          },
          "fields": [
            {
              "jsonPath": "$.byType.*",
              "name": ""
            }
          ],
          "method": "GET",
          "queryType": "query",
          "refId": "A",
          "urlPath": "/api/s3-stats"
        }
      ],
      "title": "Storage by File Type",
      "type": "piechart"
    },
    {
      "gridPos": {
        "h": 8,
        "w": 16,
        "x": 8,
        "y": 4
      },
      "id": 8,
      "targets": [
        {
          "datasource": {
            "type": "marcusolsson-json-datasource",
            "uid": "bfc1cyfos74sgd"
          },
          "fields": [
            {
              "jsonPath": "$.timeline[*].date",
              "name": "Date",
              "type": "time"
            },
            {
              "jsonPath": "$.timeline[*].sizeGB",
              "name": "Size (GB)"
            },
            {
              "jsonPath": "$.timeline[*].files",
              "name": "Files"
            }
          ],
          "method": "GET",
          "queryType": "query",
          "refId": "A",
          "urlPath": "/api/s3-stats"
        }
      ],
      "title": "Upload Timeline",
      "type": "graph",
      "xaxis": {
        "mode": "time",
        "show": true
      },
      "yaxes": [
        {
          "format": "decgbytes",
          "label": "Size (GB)",
          "show": true
        },
        {
          "format": "short",
          "label": "Files",
          "show": true
        }
      ]
    },
    {
      "fieldConfig": {
        "overrides": [
          {
            "matcher": {
              "id": "byName",
              "options": "Size (GB)"
            },
            "properties": [
              {
                "id": "unit",
                "value": "decgbytes"
              },
              {
                "id": "decimals",
                "value": 2
              }
            ]
          },
          {
            "matcher": {
              "id": "byName",
              "options": "Status"
            },
            "properties": [
              {
                "id": "custom.cellOptions",
                "value": {
                  "mode": "gradient",
                  "type": "color-text"
                }
              },
              {
                "id": "mappings",
                "value": [
                  {
                    "options": {
                      "complete": {
                        "color": "green",
                        "text": "\u2713 Complete"
                      },
                      "incomplete": {
                        "color": "red",
                        "text": "\u2717 Incomplete"
                      }
                    },
                    "type": "value"
                  }
                ]
              }
            ]
          }
        ]
      },
      "gridPos": {
        "h": 8,
        "w": 12,
        "x": 0,
        "y": 12
      },
      "id": 9,
      "options": {
        "showHeader": true,
        "sortBy": [
          {
            "desc": true,
            "displayName": "Session ID"
          }
        ]
      },
      "targets": [
        {
          "datasource": {
            "type": "marcusolsson-json-datasource",
            "uid": "bfc1cyfos74sgd"
          },
          "fields": [
            {
              "jsonPath": "$.sessions.sessions[*].id",
              "name": "Session ID"
            },
            {
              "jsonPath": "$.sessions.sessions[*].files",
              "name": "Files"
            },
            {
              "jsonPath": "$.sessions.sessions[*].sizeGB",
              "name": "Size (GB)"
            },
            {
              "jsonPath": "$.sessions.sessions[*].status",
              "name": "Status"
            }
          ],
          "method": "GET",
          "queryType": "query",
          "refId": "A",
          "urlPath": "/api/s3-stats"
        }
      ],
      "title": "Session Details",
      "type": "table"
    },
    {
      "fieldConfig": {
        "defaults": {
          "color": {
            "mode": "palette-classic"
          },
          "decimals": 2,
          "thresholds": {
            "mode": "absolute",
            "steps": [
              {
                "color": "green",
                "value": null
              }
            ]
          },
          "unit": "currencyUSD"
        }
      },
      "gridPos": {
        "h": 8,
        "w": 6,
        "x": 12,
        "y": 12
      },
      "id": 10,
      "options": {
        "displayMode": "gradient",
        "orientation": "horizontal",
        "showUnfilled": true
      },
      "targets": [
        {
          "datasource": {
            "type": "marcusolsson-json-datasource",
            "uid": "bfc1cyfos74sgd"
          },
          "fields": [
            {
              "jsonPath": "$.costs.currentMonthly",
              "name": "S3 Standard"
            },
            {
              "jsonPath": "$.costs.intelligentTiering",
              "name": "Intelligent-Tiering"
            },
            {
              "jsonPath": "$.costs.glacierDeepArchive",
              "name": "Glacier Deep Archive"
            }
          ],
          "method": "GET",
          "queryType": "query",
          "refId": "A",
          "urlPath": "/api/s3-stats"
        }
      ],
      "title": "Cost Comparison",
      "type": "bargauge"
    },
    {
      "fieldConfig": {
        "defaults": {
          "decimals": 2,
          "unit": "decgbytes"
        },
        "overrides": [
          {
            "matcher": {
              "id": "byName",
              "options": "Count"
            },
            "properties": [
              {
                "id": "unit",
                "value": "none"
              },
              {
                "id": "decimals",
                "value": 0
              }
            ]
          }
        ]
      },
      "gridPos": {
        "h": 4,
        "w": 6,
        "x": 18,
        "y": 12
      },
      "id": 11,
      "options": {
        "colorMode": "value",
        "graphMode": "none",
        "textMode": "value_and_name"
      },
      "targets": [
        {
          "datasource": {
            "type": "marcusolsson-json-datasource",
            "uid": "bfc1cyfos74sgd"
          },
          "fields": [
            {
              "jsonPath": "$.insights.videoStats.count",
              "name": "Count"
            },
            {
              "jsonPath": "$.insights.videoStats.avgGB",
              "name": "Avg Size"
            },
            {
              "jsonPath": "$.insights.videoStats.minGB",
              "name": "Min Size"
            },
            {
              "jsonPath": "$.insights.videoStats.maxGB",
              "name": "Max Size"
            }
          ],
          "method": "GET",
          "queryType": "query",
          "refId": "A",
          "urlPath": "/api/s3-stats"
        }
      ],
      "title": "Video Statistics",
      "type": "stat"
    },
    {
      "fieldConfig": {
        "defaults": {
          "decimals": 1,
          "unit": "decmbytes"
        },
        "overrides": [
          {
            "matcher": {
              "id": "byName",
              "options": "Count"
            },
            "properties": [
              {
                "id": "unit",
                "value": "none"
              },
              {
                "id": "decimals",
                "value": 0
              }
            ]
          }
        ]
      },
      "gridPos": {
        "h": 4,
        "w": 6,
        "x": 18,
        "y": 16
      },
      "id": 12,
      "options": {
        "colorMode": "value",
        "graphMode": "none",
        "textMode": "value_and_name"
      },
      "targets": [
        {
          "datasource": {
            "type": "marcusolsson-json-datasource",
            "uid": "bfc1cyfos74sgd"
          },
          "fields": [
            {
              "jsonPath": "$.insights.npzStats.count",
              "name": "Count"
            },
            {
              "jsonPath": "$.insights.npzStats.avgMB",
              "name": "Avg Size"
            },
            {
              "jsonPath": "$.insights.npzStats.minMB",
              "name": "Min Size"
            },
            {
              "jsonPath": "$.insights.npzStats.maxMB",
              "name": "Max Size"
            }
          ],
          "method": "GET",
          "queryType": "query",
          "refId": "A",
          "urlPath": "/api/s3-stats"
        }
      ],
      "title": "NPZ Data Statistics",
      "type": "stat"
    },
    {
      "fieldConfig": {
        "overrides": [
          {
            "matcher": {
              "id": "byName",
              "options": "Size (GB)"
            },
            "properties": [
              {
                "id": "unit",
                "value": "decgbytes"
              },
              {
                "id": "decimals",
                "value": 2
              }
            ]
          }
        ]
      },
      "gridPos": {
        "h": 8,
        "w": 24,
        "x": 0,
        "y": 20
      },
      "id": 13,
      "options": {
        "showHeader": true,
        "sortBy": [
          {
            "desc": true,
            "displayName": "Upload Date"
          }
        ]
      },
      "targets": [
        {
          "datasource": {
            "type": "marcusolsson-json-datasource",
            "uid": "bfc1cyfos74sgd"
          },
          "fields": [
            {
              "jsonPath": "$.processedOutputs.files[*].name",
              "name": "Filename"
            },
            {
              "jsonPath": "$.processedOutputs.files[*].sizeGB",
              "name": "Size (GB)"
            },
            {
              "jsonPath": "$.processedOutputs.files[*].date",
              "name": "Upload Date"
            }
          ],
          "method": "GET",
          "queryType": "query",
          "refId": "A",
          "urlPath": "/api/s3-stats"
        }
      ],
      "title": "Processed Outputs",
      "type": "table"
    }
  ],
  "refresh": "5m",
  "schemaVersion": 39,
  "tags": [
    "s3",
    "storage",
    "analytics"
  ],
  "time": {
    "from": "now-30d",
    "to": "now"
  },
  "timezone": "browser",
  "title": "S3 Bucket - Data Analytics",
  "uid": "d6873221-e5d6-4a21-995e-b1277c421ca8",
  "version": 1
}